pycalf/__init__.py
pycalf/metrics.py
pycalf/propensity.py
pycalf/uplift.py
pycalf/visualize.py
pycalf-0.3.0.dist-info/licenses/LICENSE
pycalf-0.3.0.dist-info/METADATA
pycalf-0.3.0.dist-info/WHEEL
pycalf-0.3.0.dist-info/top_level.txt
pycalf-0.3.0.dist-info/RECORD
