Metadata-Version: 2.4
Name: pycalf
Version: 0.3.0
Author-email: konumaru <konumaru1022@gmail.com>
License: MIT
Project-URL: repository, https://github.com/konumaru/pycalf
Project-URL: documentation, https://pycalf.readthedocs.io/en/latest/
Requires-Python: >=3.13
License-File: LICENSE
Requires-Dist: numpy>=1.18.2
Requires-Dist: pandas>=1.0.3
Requires-Dist: matplotlib>=3.2.1
Requires-Dist: scikit-learn>=1.3.1
Requires-Dist: statsmodels>=0.14.0
Provides-Extra: dev
Requires-Dist: pytest>=8.3.5; extra == "dev"
Requires-Dist: pytest-cov>=6.1.1; extra == "dev"
Requires-Dist: ruff>=0.11.5; extra == "dev"
Requires-Dist: sphinx>=8.2.3; extra == "dev"
Requires-Dist: sphinx-rtd-theme>=3.0.2; extra == "dev"
Dynamic: license-file
